pyvter/__init__.py
pyvter/base.py
pyvter/examples/__init__.py
pyvter/examples/betweenAVOVA_omega-squared.py
pyvter/misc/SimpleHTML.py
pyvter/misc/__init__.py
pyvter/misc/support.py
pyvter/misc/texttable.py
pyvter/plotting/__init__.py
pyvter/plotting/_box_plot.py
pyvter/plotting/_histogram_plot.py
pyvter/plotting/_interaction_plot.py
pyvter/plotting/_scatter_matrix.py
pyvter/plotting/_scatter_plot.py
pyvter/plotting/support.py
pyvter/stats/__init__.py
pyvter/stats/_anova.py
pyvter/stats/_anova1way.py
pyvter/stats/_chisquare1way.py
pyvter/stats/_chisquare2way.py
pyvter/stats/_correlation.py
pyvter/stats/_descriptives.py
pyvter/stats/_histogram.py
pyvter/stats/_marginals.py
pyvter/stats/_noncentral.py
pyvter/stats/_pstat.py
pyvter/stats/_stats.py
pyvter/stats/_ttest.py
pyvter/stats/qsturng.py
pyvter/tests/__init__.py
pyvter/tests/_datafile_replacer.py
pyvter/tests/support.py
pyvter/tests/test_df__delitem__.py
pyvter/tests/test_df__determine_sqlite3_type.py
pyvter/tests/test_df__setitem__.py
pyvter/tests/test_df__str__.py
pyvter/tests/test_df_are_col_lengths_equal.py
pyvter/tests/test_df_attach.py
pyvter/tests/test_df_build_sqlite3_tbl.py
pyvter/tests/test_df_insert.py
pyvter/tests/test_df_read_tbl.py
pyvter/tests/test_df_select_col.py
pyvter/tests/test_df_sort.py
pyvter/tests/test_df_validate.py
pyvter/tests/test_df_where.py
pyvter/tests/test_df_where_update.py
pyvter/tests/test_df_write.py
pyvter/tests/test_plotting_box_plot.py
pyvter/tests/test_plotting_histogram_plot.py
pyvter/tests/test_plotting_interaction_plot.py
pyvter/tests/test_plotting_scatter_matrix.py
pyvter/tests/test_plotting_scatter_plot.py
pyvter/tests/test_pt__getitem__.py
pyvter/tests/test_pt__repr__.py
pyvter/tests/test_pt__setitem__.py
pyvter/tests/test_pt__str__.py
pyvter/tests/test_pt_flatten.py
pyvter/tests/test_pt_iterators.py
pyvter/tests/test_pt_mathmethods.py
pyvter/tests/test_pt_run.py
pyvter/tests/test_pt_to_dataframe.py
pyvter-0.0.3.dist-info/METADATA
pyvter-0.0.3.dist-info/RECORD
pyvter-0.0.3.dist-info/WHEEL
pyvter-0.0.3.dist-info/top_level.txt
